{
  "data": {
    "article": {},
    "attachments": {},
    "author_id": "1739437517772926976",
    "conversation_id": "1866060260030767121",
    "created_at": "2024-12-09T11:33:55.000Z",
    "edit_controls": {
      "editable_until": "2024-12-09T12:33:55.000Z",
      "edits_remaining": 5,
      "is_edit_eligible": false
    },
    "edit_history_tweet_ids": [
      "1866083852223230081"
    ],
    "entities": {
      "mentions": [
        {
          "end": 13,
          "id": "1655758232420249602",
          "start": 0,
          "username": "Yutuanzi2375"
        }
      ]
    },
    "geo": {},
    "id": "1866083852223230081",
    "in_reply_to_user_id": "1655758232420249602",
    "lang": "zh",
    "note_tweet": {
      "entities": {}
    },
    "possibly_sensitive": false,
    "public_metrics": {
      "bookmark_count": 0,
      "impression_count": 0,
      "like_count": 0,
      "quote_count": 0,
      "reply_count": 0,
      "retweet_count": 0
    },
    "referenced_tweets": [
      {
        "id": "1866060260030767121",
        "type": "replied_to"
      }
    ],
    "reply_settings": "everyone",
    "text": "@Yutuanzi2375 全按史低算总计1244人民币，看来我大错特错了"
  },
  "includes": {
    "tweets": [
      {
        "article": {},
        "attachments": {},
        "author_id": "1739437517772926976",
        "conversation_id": "1866060260030767121",
        "created_at": "2024-12-09T11:33:55.000Z",
        "edit_controls": {
          "editable_until": "2024-12-09T12:33:55.000Z",
          "edits_remaining": 5,
          "is_edit_eligible": false
        },
        "edit_history_tweet_ids": [
          "1866083852223230081"
        ],
        "entities": {
          "mentions": [
            {
              "end": 13,
              "id": "1655758232420249602",
              "start": 0,
              "username": "Yutuanzi2375"
            }
          ]
        },
        "geo": {},
        "id": "1866083852223230081",
        "in_reply_to_user_id": "1655758232420249602",
        "lang": "zh",
        "note_tweet": {
          "entities": {}
        },
        "possibly_sensitive": false,
        "public_metrics": {
          "bookmark_count": 0,
          "impression_count": 0,
          "like_count": 0,
          "quote_count": 0,
          "reply_count": 0,
          "retweet_count": 0
        },
        "referenced_tweets": [
          {
            "id": "1866060260030767121",
            "type": "replied_to"
          }
        ],
        "reply_settings": "everyone",
        "text": "@Yutuanzi2375 全按史低算总计1244人民币，看来我大错特错了"
      },
      {
        "article": {},
        "attachments": {
          "media_keys": [
            "3_1866060256838885376",
            "3_1866060257077919744",
            "3_1866060257199566849",
            "3_1866060257157591040"
          ]
        },
        "author_id": "1655758232420249602",
        "context_annotations": [
          {
            "domain": {
              "description": "Categories within Brand Verticals that narrow down the scope of Brands",
              "id": "46",
              "name": "Business Taxonomy"
            },
            "entity": {
              "description": "Brands, companies, advertisers and every non-person handle with the profit intent related to offline and online games such as gaming consoles, tabletop games, video game publishers",
              "id": "1557696940178935808",
              "name": "Gaming Business"
            }
          }
        ],
        "conversation_id": "1866060260030767121",
        "created_at": "2024-12-09T10:00:10.000Z",
        "edit_controls": {
          "editable_until": "2024-12-09T11:00:10.000Z",
          "edits_remaining": 5,
          "is_edit_eligible": false
        },
        "edit_history_tweet_ids": [
          "1866060260030767121"
        ],
        "entities": {
          "urls": [
            {
              "display_url": "pic.x.com/BlJW8otBmY",
              "end": 38,
              "expanded_url": "https://x.com/Yutuanzi2375/status/1866060260030767121/photo/1",
              "media_key": "3_1866060256838885376",
              "start": 15,
              "url": "https://t.co/BlJW8otBmY"
            },
            {
              "display_url": "pic.x.com/BlJW8otBmY",
              "end": 38,
              "expanded_url": "https://x.com/Yutuanzi2375/status/1866060260030767121/photo/1",
              "media_key": "3_1866060257077919744",
              "start": 15,
              "url": "https://t.co/BlJW8otBmY"
            },
            {
              "display_url": "pic.x.com/BlJW8otBmY",
              "end": 38,
              "expanded_url": "https://x.com/Yutuanzi2375/status/1866060260030767121/photo/1",
              "media_key": "3_1866060257199566849",
              "start": 15,
              "url": "https://t.co/BlJW8otBmY"
            },
            {
              "display_url": "pic.x.com/BlJW8otBmY",
              "end": 38,
              "expanded_url": "https://x.com/Yutuanzi2375/status/1866060260030767121/photo/1",
              "media_key": "3_1866060257157591040",
              "start": 15,
              "url": "https://t.co/BlJW8otBmY"
            }
          ]
        },
        "geo": {},
        "id": "1866060260030767121",
        "lang": "zh",
        "note_tweet": {
          "entities": {}
        },
        "possibly_sensitive": false,
        "public_metrics": {
          "bookmark_count": 0,
          "impression_count": 165,
          "like_count": 0,
          "quote_count": 1,
          "reply_count": 3,
          "retweet_count": 0
        },
        "reply_settings": "everyone",
        "text": "没钱用了想卖掉steam了🥺 https://t.co/BlJW8otBmY"
      }
    ],
    "users": [
      {
        "created_at": "2023-12-26T00:06:59.000Z",
        "description": "",
        "id": "1739437517772926976",
        "name": "Dandelion",
        "pinned_tweet_id": "1864465117498511560",
        "profile_image_url": "https://pbs.twimg.com/profile_images/1861799971542167552/3RsWxOcr_normal.jpg",
        "protected": false,
        "public_metrics": {
          "followers_count": 608,
          "following_count": 978,
          "like_count": 7614,
          "listed_count": 1,
          "media_count": 67,
          "tweet_count": 1353
        },
        "username": "Dandelion6238",
        "verified": false
      },
      {
        "created_at": "2023-05-09T02:15:17.000Z",
        "description": "167cm，55kg，00年，应该是比较大龄了吧，无证嗑药，6月5日开始吃糖🏳️‍⚧️ 关注我会互fo /可爱的妹妹🥰@zhengzheng03（号又寄了初始号@penp58）",
        "entities": {
          "description": {
            "mentions": [
              {
                "end": 72,
                "start": 59,
                "username": "zhengzheng03"
              },
              {
                "end": 87,
                "start": 80,
                "username": "penp58"
              }
            ]
          }
        },
        "id": "1655758232420249602",
        "location": "在你心里",
        "name": "芋团子🏳️‍⚧️",
        "pinned_tweet_id": "1840936789017833803",
        "profile_image_url": "https://pbs.twimg.com/profile_images/1704477413542158336/w8horUOn_normal.jpg",
        "protected": false,
        "public_metrics": {
          "followers_count": 1512,
          "following_count": 1057,
          "like_count": 80646,
          "listed_count": 3,
          "media_count": 304,
          "tweet_count": 4397
        },
        "username": "Yutuanzi2375",
        "verified": false
      }
    ]
  }
}